flashcluster-0.3.1.dist-info/METADATA
flashcluster-0.3.1.dist-info/WHEEL
flashcluster-0.3.1.dist-info/licenses/LICENSE
flashcluster/__init__.py
flashcluster/__init__.pyi
flashcluster/flashcluster.cpython-313-x86_64-linux-gnu.so
flashcluster/py.typed
flashcluster-0.3.1.dist-info/RECORD
