Metadata-Version: 2.4
Name: flashcluster
Version: 0.3.1
Classifier: Programming Language :: Rust
Classifier: Programming Language :: Python :: Implementation :: CPython
Classifier: Programming Language :: Python :: Implementation :: PyPy
Requires-Dist: numpy>=1.24.4
License-File: LICENSE
Summary: Flashcluster, a lightning-fast hierarchical clustering package.
Author: Gabriel Bathie <gbathie.dev@gmail.com>, Guillaume Lagarde <guillaume.lagarde@gmail.com>
Author-email: Gabriel Bathie <gbathie.dev@gmail.com>, Guillaume Lagarde <guillaume.lagarde@gmail.com>
Requires-Python: >=3.8
